LICENSE
perm_security/__init__.py
perm_security/converters/__init__.py
perm_security/converters/PermissionChannelConverter.py
perm_security/MemberAdapter/__init__.py
perm_security/MemberAdapter/MemberAdapter.py
perm_security/MemberAdapter/MemberChannelAdapter.py
perm_security/MemberAdapter/MemberGuildAdapter.py
perm_security/Permission/__init__.py
perm_security/Permission/DiscordPermissions.py
perm_security/Token.py
perm_security/TokenStrategy/__init__.py
perm_security/TokenStrategy/BasicTokenStrategy.py
perm_security/TokenStrategy/MismatchPermissionException.py
perm_security/TokenStrategy/NonMemberTokenException.py
perm_security/TokenStrategy/PermissionDeniedException.py
perm_security/TokenStrategy/TokenHandlerStrategy/__init__.py
perm_security/TokenStrategy/TokenHandlerStrategy/BasicTokenHandlerStrategy.py
perm_security/TokenStrategy/TokenHandlerStrategy/TokenHandlerStrategy.py
perm_security/TokenStrategy/TokenStrategy.py
perm_security-0.2.0.dist-info/LICENSE
perm_security-0.2.0.dist-info/WHEEL
perm_security-0.2.0.dist-info/METADATA
perm_security-0.2.0.dist-info/RECORD
