Metadata-Version: 2.1
Name: perm-security
Version: 0.2.0
Summary: A package to bridge the gap between Discord's API and Perm-Banana
Home-page: https://github.com/TheJoeSmo/perm-security
License: MIT
Keywords: discord,perm-banana,token
Author: TheJoeSmo
Author-email: joesmo.joesmo12@gmail.com
Requires-Python: >=3.9,<4.0
Classifier: License :: OSI Approved :: MIT License
Classifier: Programming Language :: Python :: 3
Classifier: Programming Language :: Python :: 3.9
Requires-Dist: APScheduler (>=3.7.0,<4.0.0)
Requires-Dist: discord (>=1.7.3,<2.0.0)
Requires-Dist: perm-banana (>=0.1.1,<0.2.0)
Project-URL: Repository, https://github.com/TheJoeSmo/perm-security
